im_openai/__init__.py
im_openai/background.py
im_openai/client.py
im_openai/langchain/__init__.py
im_openai/langchain/callbacks.py
im_openai/langchain/patch.py
im_openai/langchain/util.py
im_openai/patch.py
im_openai/pii/__init__.py
im_openai/pii/data/__init__.py
im_openai/pii/data/names.json
im_openai/pii/data/names.json.LICENSE
im_openai/pii/name_recognizer.py
im_openai/pii/nlp.py
im_openai/pii/redactor.py
im_openai/pii/street_address_recognizer.py
im_openai/py.typed
im_openai/template.py
im_openai-0.15.2.dist-info/LICENSE
im_openai-0.15.2.dist-info/METADATA
im_openai-0.15.2.dist-info/WHEEL
im_openai-0.15.2.dist-info/RECORD
