Metadata-Version: 2.1
Name: im-openai
Version: 0.15.2
Summary: Wrapper library for openai to send events to the Imaginary Programming monitor
License: MIT
Author: Alec Flett
Author-email: alecf@thegp.com
Requires-Python: >=3.10,<4.0
Classifier: License :: OSI Approved :: MIT License
Classifier: Programming Language :: Python :: 3
Classifier: Programming Language :: Python :: 3.10
Classifier: Programming Language :: Python :: 3.11
Classifier: Programming Language :: Python :: 3.12
Requires-Dist: aiohttp (>=3.8.5,<4.0.0)
Requires-Dist: openai (>=0.27.9,<0.29.0)
Requires-Dist: presidio-analyzer (>=2.2.33,<3.0.0)
Requires-Dist: presidio-anonymizer (>=2.2.33,<3.0.0)
